langbench/__init__.py
langbench/base.py
langbench/benchmarks.py
langbench/metrics.py
langbench-0.0.2.dist-info/LICENSE
langbench-0.0.2.dist-info/METADATA
langbench-0.0.2.dist-info/WHEEL
langbench-0.0.2.dist-info/entry_points.txt
langbench-0.0.2.dist-info/RECORD
